Metadata-Version: 2.1
Name: odoo10-addon-l10n-be-partner-kbo-bce
Version: 10.0.1.0.2
Summary: Belgium - KBO/BCE numbers
Home-page: https://odoo-community.org/
Author: Noviat,Odoo Community Association (OCA)
Author-email: support@odoo-community.org
License: AGPL-3
Platform: UNKNOWN
Classifier: Programming Language :: Python
Classifier: Framework :: Odoo
Classifier: License :: OSI Approved :: GNU Affero General Public License v3
Requires-Python: ~=2.7
Requires-Dist: odoo10-addon-base-vat-sanitized
Requires-Dist: odoo10-addon-partner-identification
Requires-Dist: odoo (<10.1dev,>=10.0)
